eunomia_sdk_langchain/__init__.py
eunomia_sdk_langchain/document_loader.py
eunomia_sdk_langchain/retriever.py
eunomia_sdk_langchain-0.3.2.dist-info/METADATA
eunomia_sdk_langchain-0.3.2.dist-info/WHEEL
eunomia_sdk_langchain-0.3.2.dist-info/RECORD
