Metadata-Version: 2.4
Name: eunomia-sdk-langchain
Version: 0.3.2
Summary: Eunomia SDK for LangChain
Author-email: What About You team <info@whataboutyou.ai>
License-Expression: Apache-2.0
Requires-Python: >=3.10
Requires-Dist: eunomia-sdk-python>=0.3.2
Requires-Dist: langchain-core>=0.3.41
Requires-Dist: langchain>=0.3.20
